combine_files/__init__.py
combine_files/__main__.py
combine_files/cli.py
project_combiner-0.1.3.dist-info/licenses/LICENCE
project_combiner-0.1.3.dist-info/METADATA
project_combiner-0.1.3.dist-info/WHEEL
project_combiner-0.1.3.dist-info/entry_points.txt
project_combiner-0.1.3.dist-info/top_level.txt
project_combiner-0.1.3.dist-info/RECORD
