Metadata-Version: 2.4
Name: project-combiner
Version: 0.1.3
Summary: Concatenate text-like files in a directory tree with Typer-powered CLI.
Author-email: Muhammad Luay <muhammadluay45@gmail.com>
License-Expression: MIT
Project-URL: Homepage, https://pypi.org/project/project-combiner
Project-URL: Source, https://github.com/muhammad-luay/context-tools
Project-URL: Issues, https://github.com/muhammad-luay/context-tools/issues
Classifier: Programming Language :: Python :: 3
Classifier: Environment :: Console
Classifier: Intended Audience :: Developers
Classifier: Topic :: Utilities
Requires-Python: >=3.8
License-File: LICENCE
Requires-Dist: typer>=0.9
Requires-Dist: colorama; sys_platform == "win32"
Provides-Extra: all
Requires-Dist: typer[all]; extra == "all"
Requires-Dist: pathspec; extra == "all"
Requires-Dist: tqdm; extra == "all"
Requires-Dist: pyperclip; extra == "all"
Dynamic: license-file
